nurapy/__about__.py
nurapy/__init__.py
nurapy/_helpers.py
nurapy/protocol/__init__.py
nurapy/protocol/rx_handler.py
nurapy/protocol/command/__init__.py
nurapy/protocol/command/get_device_capabilities.py
nurapy/protocol/command/get_id_buffer.py
nurapy/protocol/command/get_id_buffer_meta.py
nurapy/protocol/command/get_mode.py
nurapy/protocol/command/get_reader_info.py
nurapy/protocol/command/inventory.py
nurapy/protocol/command/inventory_stream.py
nurapy/protocol/command/module_setup.py
nurapy/transport/__init__.py
nurapy/transport/serial.py
nurapy-1.0.0.dist-info/METADATA
nurapy-1.0.0.dist-info/WHEEL
nurapy-1.0.0.dist-info/licenses/LICENSE.txt
nurapy-1.0.0.dist-info/RECORD
